easymyai/Ai_Funcs.py
easymyai/Code_My_AI.py
easymyai/Ensemble_AI.py
easymyai/__init__.py
easymyai-5.0.dist-info/METADATA
easymyai-5.0.dist-info/WHEEL
easymyai-5.0.dist-info/top_level.txt
easymyai-5.0.dist-info/RECORD
