Metadata-Version: 2.1
Name: easymyai
Version: 5.0
Summary: Easy creation of your own simple neural network
Home-page: https://github.com/ZenSam7/My_AI
Author: ZenSam7
Author-email: samkirich@yandex.ru
Requires-Dist: numpy >=1.26.2
